cachelib/__init__.py
cachelib/base.py
cachelib/file.py
cachelib/memcached.py
cachelib/py.typed
cachelib/redis.py
cachelib/serializers.py
cachelib/simple.py
cachelib/uwsgi.py
cachelib-0.8.0.dist-info/LICENSE.rst
cachelib-0.8.0.dist-info/METADATA
cachelib-0.8.0.dist-info/WHEEL
cachelib-0.8.0.dist-info/top_level.txt
cachelib-0.8.0.dist-info/RECORD
