Metadata-Version: 2.1
Name: cachelib
Version: 0.8.0
Summary: A collection of cache libraries in the same API interface.
Home-page: https://github.com/pallets/cachelib/
Maintainer: Pallets
Maintainer-email: contact@palletsprojects.com
License: BSD-3-Clause
Project-URL: Donate, https://palletsprojects.com/donate
Project-URL: Documentation, https://cachelib.readthedocs.io/
Project-URL: Changes, https://cachelib.readthedocs.io/changes/
Project-URL: Source Code, https://github.com/pallets/cachelib/
Project-URL: Issue Tracker, https://github.com/pallets/cachelib/issues/
Project-URL: Twitter, https://twitter.com/PalletsTeam
Project-URL: Chat, https://discord.gg/pallets
Platform: UNKNOWN
Classifier: Development Status :: 5 - Production/Stable
Classifier: Intended Audience :: Developers
Classifier: License :: OSI Approved :: BSD License
Classifier: Operating System :: OS Independent
Classifier: Programming Language :: Python
Requires-Python: >=3.7
